hdhr/__init__.py
hdhr/adapter.py
hdhr/adapter_types.py
hdhr/constants.py
hdhr/externals.py
hdhr/libhdhr.py
hdhr/log_config.py
hdhr/types.py
hdhr/utility.py
hdhr-0.0.8.dist-info/LICENSE
hdhr-0.0.8.dist-info/METADATA
hdhr-0.0.8.dist-info/WHEEL
hdhr-0.0.8.dist-info/top_level.txt
hdhr-0.0.8.dist-info/zip-safe
hdhr-0.0.8.dist-info/RECORD
