Metadata-Version: 2.1
Name: hdhr
Version: 0.0.8
Summary: HDHomeRun interface library for Python 3.
Home-page: https://github.com/burnnat/hdhr
Author: Nat Burns
Author-email: nbaccount@burnskids.com
License: GPL 2
Keywords: tv television tuner tvtuner hdhomerun
Platform: UNKNOWN
Classifier: Development Status :: 4 - Beta
Classifier: Natural Language :: English
Classifier: Topic :: Software Development :: Libraries :: Python Modules
Classifier: Topic :: Multimedia :: Video :: Capture
Requires-Dist: setuptools
